example-project/__init__.py
example-project/some_package/some_module.py
example-project/some_package/__init__.py
bamboo_api-0.0.1.dist-info/WHEEL
bamboo_api-0.0.1.dist-info/top_level.txt
bamboo_api-0.0.1.dist-info/RECORD
bamboo_api-0.0.1.dist-info/METADATA
bamboo_api-0.0.1.dist-info/DESCRIPTION.rst
bamboo_api-0.0.1.dist-info/metadata.json
bamboo_api/api.py
bamboo_api/__init__.py
