Metadata-Version: 2.0
Name: bamboo-api
Version: 0.0.1
Summary: Bamboo API Client
Home-page: https://github.com/liocuevas/python-bamboo-api
Author: Lionel Cuevas
Author-email: liocuevas@gmail.com
License: MIT
Keywords: api bamboo rest api client
Platform: UNKNOWN
Classifier: Development Status :: 3 - Alpha
Classifier: Environment :: Console
Classifier: Intended Audience :: End Users/Desktop
Classifier: License :: OSI Approved :: MIT License
Classifier: Operating System :: Unix
Classifier: Programming Language :: Python :: 3
Requires-Dist: requests
